{
  "assets": {
    "groundStone": {
      "type": "image",
      "source": "assets/images/sandstone_64.png"
    },
    "groundMountain": {
      "type": "image",
      "source": "assets/images/mountain_64.png"
    },
    "groundSand": {
      "type": "image",
      "source": "assets/images/sand_64.png"
    },
    "groundGrass": {
      "type": "image",
      "source": "assets/images/grass_64.png"
    },
    "groundTiled": {
      "type": "image",
      "source": "assets/images/tiled_64.png"
    },
    "robot3Dblue": {
      "type": "image",
      "source": "assets/images/robot_3Dblue.png"
    },
    "robot3Dgreen": {
      "type": "image",
      "source": "assets/images/robot_3Dgreen.png"
    },
    "robot3Dred": {
      "type": "image",
      "source": "assets/images/robot_3Dred.png"
    },
    "robot3Dyellow": {
      "type": "image",
      "source": "assets/images/robot_3Dyellow.png"
    },
    "bullet": {
      "type": "image",
      "source": "assets/images/tank_bullet3.png"
    },
    "heart": {
      "type": "image",
      "source": "assets/images/hud_heartFull.png"
    },
    "crateAmmo": {
      "type": "image",
      "source": "assets/images/tanks_crateAmmo.png"
    },
    "crateArmor": {
      "type": "image",
      "source": "assets/images/tanks_crateArmor.png"
    },
    "crateRepair": {
      "type": "image",
      "source": "assets/images/tanks_crateRepair.png"
    },
    "crateWood": {
      "type": "image",
      "source": "assets/images/tanks_crateWood.png"
    }
  },
  "groups": [
    "background",
    "spawners",
    "chests",
    "robots"
  ],
  "prefabs": {
    "background": {
      "type": "tileSprite",
      "position": {
        "x": 0,
        "y": 0
      },
      "properties": {
        "group": "background",
        "key": "groundTiled",
        "size": {
          "width": 640,
          "height": 360
        },
        "fixedToCamera": true
      }
    },
    "robotSpawner": {
      "type": "robotSpawner",
      "position": {
        "x": 0,
        "y": 0
      },
      "properties": {
        "key": "",
        "group": "spawners",
        "pool": "robots",
        "mode": "once",
        "spawnTimeInSeconds": {
          "min": 1,
          "max": 3
        }
      }
    },
    "chestSpawner": {
      "type": "chestSpawner",
      "position": {
        "x": 0,
        "y": 0
      },
      "properties": {
        "key": "",
        "group": "spawners",
        "pool": "chests",
        "mode": "limited",
        "limit": 5,
        "spawnTimeInSeconds": {
          "min": 1,
          "max": 3
        }
      }
    }
  }
}